pymorpheus/__init__.py
pymorpheus-0.1.6.dist-info/LICENSE.txt
pymorpheus-0.1.6.dist-info/METADATA
pymorpheus-0.1.6.dist-info/WHEEL
pymorpheus-0.1.6.dist-info/top_level.txt
pymorpheus-0.1.6.dist-info/RECORD
