Metadata-Version: 2.1
Name: pymorpheus
Version: 0.1.6
Summary: Morpheus API wrapper for Python 3
Home-page: UNKNOWN
Author: Nick Celebic
Author-email: nick@celebic.net
License: MIT License
Platform: UNKNOWN
Classifier: Programming Language :: Python :: 3
Classifier: License :: OSI Approved :: MIT License
Classifier: Operating System :: OS Independent
License-File: LICENSE.txt
Requires-Dist: requests
Requires-Dist: urllib3
